alien_ai_obfuscated.py
alien_ai_assistant-1.0.0.dist-info/LICENSE
alien_ai_assistant-1.0.0.dist-info/METADATA
alien_ai_assistant-1.0.0.dist-info/WHEEL
alien_ai_assistant-1.0.0.dist-info/entry_points.txt
alien_ai_assistant-1.0.0.dist-info/top_level.txt
alien_ai_assistant-1.0.0.dist-info/RECORD
