Metadata-Version: 2.1
Name: alien-ai-assistant
Version: 1.0.0
Summary: Advanced AI assistant for developers and content creators
Home-page: https://github.com/alien-tech/alien-ai-assistant
Author: Alien Technologies Inc
Author-email: support@alien-tech.dev
License: Proprietary
Project-URL: Bug Reports, https://github.com/alien-tech/alien-ai-assistant/issues
Project-URL: Source, https://github.com/alien-tech/alien-ai-assistant
Project-URL: Payment, https://paypal.me/Sendec
Project-URL: Support, https://github.com/alien-tech/alien-ai-assistant/issues
Keywords: ai,gpt,assistant,code,content,automation
Platform: any
Classifier: Development Status :: 5 - Production/Stable
Classifier: Intended Audience :: Developers
Classifier: License :: Other/Proprietary License
Classifier: Operating System :: OS Independent
Classifier: Programming Language :: Python :: 3
Classifier: Programming Language :: Python :: 3.7
Classifier: Programming Language :: Python :: 3.8
Classifier: Programming Language :: Python :: 3.9
Classifier: Programming Language :: Python :: 3.10
Classifier: Programming Language :: Python :: 3.11
Classifier: Programming Language :: Python :: 3.12
Classifier: Topic :: Software Development :: Libraries :: Python Modules
Classifier: Topic :: Terminals
Classifier: Topic :: Utilities
Requires-Python: >=3.7
License-File: LICENSE
Requires-Dist: click>=8.0.0
Requires-Dist: colorama>=0.4.0
Requires-Dist: requests>=2.25.0
Requires-Dist: rich>=10.0.0
